kidde_homesafe.py
kidde_homesafe-0.0.3.dist-info/LICENSE
kidde_homesafe-0.0.3.dist-info/METADATA
kidde_homesafe-0.0.3.dist-info/WHEEL
kidde_homesafe-0.0.3.dist-info/top_level.txt
kidde_homesafe-0.0.3.dist-info/RECORD
